[
  {
    "userId": 1,
    "firstName": "Michael",
    "lastName": "Thompson",
    "email": "michael.thompson@example.com",
    "username": "mthompson",
    "department": "Quality",
    "isActive": true
  },

  {
    "userId": 2,
    "firstName": "John",
    "lastName": "Carter",
    "email": "john.carter@example.com",
    "username": "jcarter",
    "department": "Engineering",
    "isActive": true
  },

  {
    "userId": 5,
    "firstName": "Emma",
    "lastName": "Johnson",
    "email": "emma.johnson@example.com",
    "username": "ejohnson",
    "department": "Operations",
    "isActive": true
  },

  {
    "userId": 7,
    "firstName": "Olivia",
    "lastName": "Martinez",
    "email": "olivia.martinez@example.com",
    "username": "omartinez",
    "department": "Purchasing",
    "isActive": true
  },
  {
    "userId": 13,
    "firstName": "Benjamin",
    "lastName": "Moore",
    "email": "benjamin.moore@example.com",
    "username": "bmoore",
    "department": "Admin",
    "isActive": true
  }
]